dataset/generic_dataset.py
dataset/generic_dataset_test.py
model/instantiate_searched_model.py
model/components/components.py
model/core_routines/__init__.py
model/core_routines/forward_backward_passes.py
model/core_routines/forward_backward_passes_old.py
model/metrics/__init__.py
model/metrics/mIoU_tst.py
model/metrics/metrics_aggregator.py
tutorials/example_configs/chargrid_fixed.py
tutorials/example_configs/chargrid_searched.py
tutorials/example_configs/min_viable_fixed_arch.py
tutorials/example_configs/min_viable_search_space.py
utils/count_parameters.py
utils/get_paths.py
utils/helper_script.py
utils/load_image.py
utils/parse_config.py
utils/printing.py
utils/sampling.py
utils/test_generator.py
encdecmeta-0.0.3.dist-info/METADATA
encdecmeta-0.0.3.dist-info/WHEEL
encdecmeta-0.0.3.dist-info/entry_points.txt
encdecmeta-0.0.3.dist-info/top_level.txt
encdecmeta-0.0.3.dist-info/RECORD
